{
  "posts": [
    {
      "id": "1",
      "title": "json-server",
      "userId": "1"
    },
    {
      "id": "2",
      "title": "json-server",
      "userId": "2"
    }
  ],
  "comments": [
    {
      "id": "1",
      "body": "some comment",
      "postId": "1"
    }
  ],
  "users": [
    {
      "id": "1",
      "username": "admin",
      "password": "123"
    },
    {
      "id": "2",
      "username": "user",
      "password": "12345"
    }
  ],
  "profile": {
    "first": "Илья",
    "lastname": "Курындин",
    "age": 31,
    "currency": "EUR",
    "country": "Belarus",
    "city": "Москва",
    "username": "admin",
    "avatar": "https://silikonmold.ru/image/cache/catalog/2021/september/leopard_29x18sm-1200x1200.jpg"
  }
}